coeus_sphinx_theme/__init__.py
coeus_sphinx_theme/breadcrumbs.html.jinja
coeus_sphinx_theme/contributors.html.jinja
coeus_sphinx_theme/footer.html.jinja
coeus_sphinx_theme/layout.html
coeus_sphinx_theme/mini_sidebar.html.jinja
coeus_sphinx_theme/navbar.html.jinja
coeus_sphinx_theme/navbar_links.html.jinja
coeus_sphinx_theme/notebook.html.jinja
coeus_sphinx_theme/page.html
coeus_sphinx_theme/previous_next.html.jinja
coeus_sphinx_theme/search.html
coeus_sphinx_theme/searchbox.html.jinja
coeus_sphinx_theme/sidebar.html.jinja
coeus_sphinx_theme/theme.conf
coeus_sphinx_theme/title_hero.html.jinja
coeus_sphinx_theme/toc.html.jinja
coeus_sphinx_theme/utils.py
coeus_sphinx_theme/video.html.jinja
coeus_sphinx_theme/youtube_video.html.jinja
coeus_sphinx_theme/extensions/__init__.py
coeus_sphinx_theme/extensions/announcement.py
coeus_sphinx_theme/extensions/contributors.py
coeus_sphinx_theme/extensions/general_video.py
coeus_sphinx_theme/extensions/headshots.py
coeus_sphinx_theme/extensions/notebook.py
coeus_sphinx_theme/extensions/roles.py
coeus_sphinx_theme/extensions/step_flow.py
coeus_sphinx_theme/extensions/title_hero.py
coeus_sphinx_theme/extensions/youtube_video.py
coeus_sphinx_theme/static/animations.css
coeus_sphinx_theme/static/coeus.css
coeus_sphinx_theme/static/coeus.js
coeus_sphinx_theme/static/github.css
coeus_sphinx_theme/static/main.js
coeus_sphinx_theme/static/xarray.css
coeus_sphinx_theme-2024.11.1.dist-info/LICENSE
coeus_sphinx_theme-2024.11.1.dist-info/METADATA
coeus_sphinx_theme-2024.11.1.dist-info/WHEEL
coeus_sphinx_theme-2024.11.1.dist-info/entry_points.txt
coeus_sphinx_theme-2024.11.1.dist-info/top_level.txt
coeus_sphinx_theme-2024.11.1.dist-info/RECORD
