Metadata-Version: 2.1
Name: coeus-sphinx-theme
Version: 2024.11.1
Summary: A Sphinx Documentation Theme.
Author-email: Akshay Mestry <xa@mes3.dev>
License: MIT License
Project-URL: Code, https://github.com/xames3/coeus-sphinx-theme
Project-URL: Download, https://pypi.org/project/coeus-sphinx-theme/
Project-URL: Homepage, https://github.com/xames3/coeus-sphinx-theme/
Project-URL: Issue tracker, https://github.com/xames3/coeus-sphinx-theme/issues
Keywords: coeus,sphinx,python,nasa
Classifier: Development Status :: 5 - Production/Stable
Classifier: Framework :: Sphinx :: Theme
Classifier: Intended Audience :: Developers
Classifier: License :: OSI Approved :: MIT License
Classifier: Operating System :: OS Independent
Classifier: Programming Language :: Python
Classifier: Programming Language :: Python :: 3.11
Classifier: Programming Language :: Python :: 3.12
Classifier: Programming Language :: Python :: 3.13
Classifier: Topic :: Documentation
Classifier: Topic :: Software Development :: Documentation
Requires-Python: >=3.11
License-File: LICENSE
Requires-Dist: bs4
Requires-Dist: jupyter-cell
Requires-Dist: pytube
Requires-Dist: sphinx
Requires-Dist: sphinx-carousel
Requires-Dist: sphinx-copybutton
Requires-Dist: sphinx-tags
Requires-Dist: sphinx-design
Requires-Dist: sphinxext-opengraph
Requires-Dist: sphinxcontrib-jquery
